<?xml version="1.0" encoding="utf-8" ?>
<!DOCTYPE form [
    <!ENTITY languages SYSTEM "Templates/Languages.xml">
    <!ENTITY regexs SYSTEM "Templates/Regexs.xml">
    <!ENTITY state SYSTEM "Templates/ChangeTermsConditionsState.xml">
    <!ENTITY pre_payscaletype_payscalelevel SYSTEM "Defaults/Predefined_PayScaleType_PayScaleLevel.xml">
    <!ENTITY data_costcentre SYSTEM "Data/Data_CostCentre.xml">
    <!ENTITY data_country SYSTEM "Data/Data_Country.xml">
    <!ENTITY data_jobtitle SYSTEM "Data/Data_JobTitle.xml">
    <!ENTITY data_localjobtitle SYSTEM "Data/Data_LocalJobTitle.xml">
    <!ENTITY data_linemanager SYSTEM "Data/Data_LineManager.xml">
    <!ENTITY data_changeallowancetype SYSTEM "Data/Data_Change_AllowancesTypes.xml">
    <!ENTITY data_typeofbenefit SYSTEM "Data/Data_Change_TypeOfBenefit.xml">
    <!ENTITY data_primarysite SYSTEM "Data/Data_PrimarySite.xml">
]>

<form id="50" guid="9F3949A4-EA0A-4C97-B0AB-1F534BCCFEB8" customerId="29">
    &languages;
    &regexs;
    &state;

    <fields>
        <!--Tab ServiceRequestDetails-->
        <tab name="#ServiceRequestDetails" label="Service Request Details">
            <element name="Co-WorkerGlobalviewID" type="text" label="Co-Worker Globalview ID" mandatory="1" casefield="reportedby" HcmData="1" SortOrder="1">
                <regex inherit="employeeno" message="" pattern=""></regex>
            </element>
            <element name="FirstName" type="text" label="Co-Worker First Name" mandatory="1" casefield="persons_name" HcmData="1" SortOrder="2"></element>
            <element name="LastName" type="text" label="Co-Worker Last name" mandatory="1" casefield="persons_phone" HcmData="1" SortOrder="3"></element>
            <element name="IKEAEmailAddress" type="text" label="IKEA Email Address" HcmData="1" SortOrder="4">
                <regex inherit="email" message="" pattern=""></regex>
            </element>
            <element name="IKEANetworkID" type="text"  label="IKEA Network ID" HcmData="1" SortOrder="5"></element>
            <element name="Company" type="text" label="Company" mandatory="1"></element>
            <element name="BusinessUnit" type="text" label="Business Unit" mandatory="1" HcmData="1" SortOrder="6"></element>
            <element name="ServiceArea" type="text" label="Function"></element>
            <element name="Department" type="text" label="Department" HcmData="1" SortOrder="7"></element>
            <element name="ChangeType" type="select" label="Change Type?" HcmData="1" SortOrder="10">
                <options>
                    <option value=""></option>
                    <option value="ONLY Pay Change">ONLY Pay Change</option>
                    <option value="ONLY Change work hours">ONLY Change work hours</option>
                    <option value="ONLY Cost Centre Change">ONLY Cost Centre Change</option>
                    <option value="ONLY extend temporary contract">ONLY extend temporary contract</option>
                    <option value="ONLY Temporary to Permanent contract">ONLY Temporary to Permanent contract</option>
                    <option value="Promotion">Promotion</option>
                    <option value="Lateral Move">Lateral Move</option>
                    <option value="Demotion">Demotion</option>
                    <option value="Re-organisation">Re-organisation</option>
                    <option value="Change in International Assignment">Change in International Assignment</option>                  
                </options>
            </element>
            <element name="ChangeValidFrom" type="date" label="Change Valid from:" mandatory="1" format="dd.MM.yyyy" casefield="plandate" HcmData="1" SortOrder="8">
                <regex inherit="date" pattern="" message=""></regex>
            </element>
            <element name="ChangeValidTo" type="date" label="Change Valid to:" mandatory="1" default="31.12.9999" format="dd.MM.yyyy" HcmData="1" SortOrder="9">
                <regex inherit="date" pattern="" message=""></regex>
                <laterThanOrEqual name="ChangeValidFrom" message="This date cannot be earlier than Change valid from date."></laterThanOrEqual>
            </element>
            <element name="ServiceRequestPriority" type="select" label="Service Request Priority" mandatory="1" default="Standard" casefield="status_id">
                <options>
                    <option value=""></option>
                    <option value="Urgent">Urgent</option>
                    <option value="Standard">Standard</option>
                </options>
            </element>

            <!--Permanent Address-->
            <element type="text" name="PermanentAddressLine1" label="Address line 1" formfieldidentifier="E1P0006.STRAS:1" HcmData="1" SortOrder="119"></element>
            <element type="text" name="PermanentAddressLine2" label="Address line 2" formfieldidentifier="E1P0006.HSNMR:1" HcmData="1" SortOrder="120"></element>
            <element type="text" name="PermanentAddressLine3" label="Address line 3" formfieldidentifier="E1P0006.POSTA:1" HcmData="1" SortOrder="121"></element>
            <element type="text" name="PermanentPostalCode" label="Postal code" formfieldidentifier="E1P0006.PSTLZ:1" HcmData="1" SortOrder="122">
                <regex inherit="postcode" message="" pattern=""></regex>
                <validateIf name="PermanentCountry">Netherlands</validateIf>
            </element>
            <element type="text" name="PermanentCity" label="City" formfieldidentifier="E1P0006.ORT01:1" HcmData="1" SortOrder="123"></element>
            <element type="search-select" source="1" name="PermanentCountry" label="Country" default="Netherlands" formfieldidentifier="E1P0006.LAND1:1" HcmData="1" SortOrder="124">
                &data_country;
            </element>

            <!--Internal Log Note-->
            <element type="textarea" name="InternalLogNote" label="Internal Log Note"></element>

        </tab>

        <!--Tab OrganisationalAssignment-->
        <tab name="#OrganisationalAssignment" label="Organisational Assignment">
            <!--Organisation Assignment-->
            <element type="hidden" name="OrganisationCountry" label="Country" default="Netherlands" HcmData="1" SortOrder="17"></element>
            <element type="select" source="database" name="NewCompany" label="Company" mandatory="1" formfieldidentifier="E1P0001.BUKRS" casefield="region_id" HcmData="1" SortOrder="18"></element>
            <!-- mandatory -->
            <element type="select" source="database" name="NewBusinessUnit" label="Business Unit" mandatory="1" formfieldidentifier="E1P0001.WERKS" casefield="department_id" HcmData="1" SortOrder="19"></element>
            <!-- mandatory -->
            <element type="select" source="database" name="NewServiceArea" label="Function" formfieldidentifier="E1P0001.BTRTL" HcmData="1" SortOrder="21"></element>
            <!-- mandatory -->
            <element type="select" source="database" name="NewDepartment" label="Department" formfieldidentifier="E1P0001.ORGEH" casefield="ou_id" HcmData="1" SortOrder="20"></element>
            <!-- mandatory -->
            <element type="search-select" name="HomeCostCentre" source="1"  label="Cost Centre" formfieldidentifier="E1P0001.KOSTL">
                <!--customid="changeModule"-->
                &data_costcentre;
            </element>
            <element type="text" name="CostAllocation" label="Cost Allocation" default="100">                
                <regex inherit="num100" pattern="" message=""></regex>
            </element>
            <element type="search-select" name="CrossChargeCostCentre" label="Cost Centre" formfieldidentifier="E1P0027.KOSTL">
                &data_costcentre;
                <mandatoryIfNotEqual name="CostAllocation">100</mandatoryIfNotEqual>
            </element>
          
            <!--Job-->

            <!-- mandatory -->
            <element type="search-select" name="LocalJobTitle" label="Position Title (Local Job Name)" HcmData="1" SortOrder="11">
              &data_localjobtitle;
            </element>
            <element type="search-select" name="JobTitle" label="Job Title (Global Catalogue)" formfieldidentifier="E1P0001.STELL" HcmData="1" SortOrder="12">
                &data_jobtitle;
            </element>           
            <element type="select" name="NewPosition" label="New Position?" default="Fill Vacant Position" HcmData="1" SortOrder="13">
                <options>
                    <option value=""></option>
                    <option value="New Position">New Position</option>
                    <option value="Fill Vacant Position">Fill Vacant Position</option>
                    <option value="New Position for VAP store?">New Position for VAP store?</option>
                </options>
            </element>
            <element type="search-select" name="ReportsToLineManager" label="Reports to Line Manager" formfieldidentifier="E1P9000.PERNRMGR" HcmData="1" SortOrder="14">
                &data_linemanager;
            </element>
            <element type="select" name="AcknowledgedManagerInCLA" label="Acknowledged as managers in terms of CLA" HcmData="1" SortOrder="15">
                <options>
                    <option value=""></option>
                    <option value="Yes">Yes</option>
                    <option value="No">No</option>
                </options>
            </element>
            <element type="select" name="ResidencePermitRestriction" label="Residence permit restriction?" HcmData="1" SortOrder="16">
                <options>
                    <option value=""></option>
                    <option value="Yes">Yes</option>
                    <option value="No">No</option>
                </options>
            </element>
            <element type="select" name="EmploymentCategory" label="Employment Category" formfieldidentifier="E1P0001.PERSG:2" HcmData="1" SortOrder="26">
                <options>
                    <option value=""></option>
                    <option value="Permanent">Permanent</option>
                    <option value="Temporary">Temporary</option>
                    <option value="Apprentice">Apprentice</option>
                    <option value="Holiday Co-Worker">Holiday Co-Worker</option>
                    <option value="Detached">Detached</option>
                    <option value="Expat (TE)">Expat (TE)</option>
                </options>
            </element>
            <element name="ContractEndDate" type="date" format="dd.MM.yyyy" label="Contract End Date" HcmData="1" SortOrder="27">
                <regex inherit="date" pattern="" message=""></regex>                
                <mandatoryIfNotEqual name="EmploymentCategory">Permanent</mandatoryIfNotEqual>
                <laterThanOrEqual name="ChangeValidFrom" message="This date cannot be earlier than Change valid from date."></laterThanOrEqual>
            </element>
            <element name="ContractedHours" type="text" label="Contracted Hours" formfieldidentifier="E1P0007.WOSTD" HcmData="1" SortOrder="25">
                <regex inherit="numMax40" pattern="" message=""></regex>
            </element>       
            <element type="select" name="ContractType" label="Contract Type" HcmData="1" SortOrder="22">
                <options>
                    <option value=""></option>
                    <option value="Part Time">Part Time</option>
                    <option value="Full Time">Full Time</option>
                </options>
            </element>
            <element name="ProbationPeriod" type="select" label="Probation period?" default="No" HcmData="1" SortOrder="23">
                <options>
                    <option value="No">No</option>
                    <option value="Yes">Yes</option>
                </options>
            </element>
            <element name="ProbationEndDate" type="date" label="Probation end date" format="dd.MM.yyyy" HcmData="1" SortOrder="24">               
                <regex inherit="date" pattern="" message=""></regex>
            </element>
            <!--CDS-->
            <element name="PrimarySite" type="select" label="Primary Site">
                &data_primarysite;
            </element>
            <element name="TECApprover" type="search-select" label="TEC Approver">
                &data_linemanager;
            </element>
            <element name="HelpDesk" type="text" label="Help Desk" default="ICC3 HBG Retail"></element>

            <element type="text" name="NameOfSchool" label="Name Of School">
                <mandatoryIf name="EmploymentCategory">Apprentice</mandatoryIf>
            </element>
            <element type="text" name="NameOfEducation" label="Name Of Education">
                <mandatoryIf name="EmploymentCategory">Apprentice</mandatoryIf>
            </element>
            <element type="text" name="CityEducationSchool" label="City Education School">
                <mandatoryIf name="EmploymentCategory">Apprentice</mandatoryIf>
            </element>
            <element type="text" name="LevelOfEducation" label="Level Of Education">
                <mandatoryIf name="EmploymentCategory">Apprentice</mandatoryIf>
            </element>
            <element type="text" name="MentorAtIKEA" label="Mentor At IKEA">
                <mandatoryIf name="EmploymentCategory">Apprentice</mandatoryIf>
            </element>
        </tab>

        <!--Tab: Payment Information-->
        <tab name="#Payment" label="Payment Information">
            <element type="select" name="PayrollCategory" label="Payroll Category" HcmData="1" SortOrder="28">
                <options>
                    <option value=""></option>
                    <option value="Hourly">Hourly</option>
                    <option value="Monthly">Monthly</option>
                    <option value="Juvenile Hourly">Juvenile Hourly</option>
                    <option value="Juvenile Monthly">Juvenile Monthly</option>
                    <option value="No Salary">No Salary</option>
                    <option value="MT/Dep/SM">MT/Dep/SM</option>
                </options>
            </element>           
            <element type="text" name="BasicPayAmount" label="Basic Pay Amount" HcmData="1" SortOrder="29">
                <regex inherit="amountwithdelimiter" pattern="" message=""></regex>                
            </element>
            <element type="select" name="PayScaleType" label="Pay Scale Type" default="IKEA NL CAO" HcmData="1" SortOrder="30">
              &pre_payscaletype_payscalelevel;
                <options>
                    <option value=""></option>
                    <option value="IKEA NL CAO">IKEA NL CAO</option>
                    <option value="IKEA NL geen CAO">IKEA NL geen CAO</option>
                    <option value="IKEA Competence">IKEA Competence</option>
                </options>
            </element>
            <element type="select" name="PayScaleLevel" label="Pay Scale Level/IPE" HcmData="1" SortOrder="31">
                <options>
                    <option value=""></option>
                    <option value="0">0</option>
                    <option value="1">1</option>
                    <option value="2">2</option>
                    <option value="3">3</option>
                    <option value="4">4</option>
                    <option value="5">5</option>
                    <option value="6">6</option>
                    <option value="7">7</option>
                    <option value="8">8</option>
                    <option value="9">9</option>
                    <option value="10">10</option>
                    <option value="11">11</option>
                    <option value="12">12</option>
                    <option value="13">13</option>
                    <option value="14">14</option>
                    <option value="44">44</option>
                    <option value="45">45</option>
                    <option value="46">46</option>
                    <option value="47">47</option>
                    <option value="48">48</option>
                    <option value="49">49</option>
                    <option value="50">50</option>
                    <option value="51">51</option>
                    <option value="52">52</option>
                    <option value="53">53</option>
                    <option value="54">54</option>
                    <option value="55">55</option>
                    <option value="56">56</option>
                    <option value="57">57</option>
                    <option value="58">58</option>
                    <option value="59">59</option>
                    <option value="60">60</option>
                    <option value="61">61</option>
                    <option value="62">62</option>
                    <option value="63">63</option>
                    <option value="64">64</option>
                    <option value="65">65</option>
                    <option value="66">66</option>
                </options>
            </element>
            <element type="select" name="BasicPayChangeReason" label="Basic Pay Change Reason">
                <mandatoryIf name="ChangeType">ONLY Pay Change</mandatoryIf>
                <options>
                    <option value=""></option>
                    <option value="Re-classification">Re-classification</option>
                    <option value="Individual increase">Individual increase</option> 
                    <option value="Adjustment desired (regular) level">Adjustment desired (regular) level</option>
                    <option value="Adjustment seniority (growth) level">Adjustment seniority (growth) level</option>

                </options>
            </element>
            <element type="hidden" name="Allowances" default="1"></element>
            <element type="select" name="AllowancesType" label="Allowance Type" HcmData="1" SortOrder="32">
                &data_changeallowancetype;
            </element>
            <element type="select" name="AllowancesPaymentType" label="Payment Type" HcmData="1" SortOrder="33">
                <mandatoryIfNotEmpty name="AllowancesType"></mandatoryIfNotEmpty>
                <options>
                    <option value=""></option>
                    <option value="One Time">One Time</option>
                    <option value="Recurring">Recurring</option>
                </options>
            </element>
            <element type="text" name="AllowancesAmountUnits" label="Amount/Units" HcmData="1" SortOrder="34">
                <mandatoryIfNotEmpty name="AllowancesType"></mandatoryIfNotEmpty>
                <regex inherit="amountwithdelimiter" pattern="" message=""></regex>
            </element>
            <element type="select" name="AllowancesNetGross" label="Net/Gross" HcmData="1" SortOrder="35">
                <mandatoryIfNotEmpty name="AllowancesType"></mandatoryIfNotEmpty>
                <options>
                    <option value=""></option>
                    <option value="Net">Net</option>
                    <option value="Gross">Gross</option>
                </options>
            </element>
            <element type="date" name="AllowancesValidFrom" label="Valid from:" format="dd.MM.yyyy" HcmData="1" SortOrder="36">
                <mandatoryIfNotEmpty name="AllowancesType"></mandatoryIfNotEmpty>
                <regex inherit="date" pattern="" message=""></regex>
                <laterThanOrEqual name="ChangeValidFrom" message="This date cannot be earlier than Change valid from date."></laterThanOrEqual>
            </element>
            <element type="date" name="AllowancesValidTo" label="Valid to:"  default="31.12.9999" format="dd.MM.yyyy" HcmData="1" SortOrder="37">
                <regex inherit="date" pattern="" message=""></regex>
            </element>
            <element type="select" name="AllowancesType2" label="Allowance Type" HcmData="1" SortOrder="38">
                &data_changeallowancetype;
            </element>
            <element type="select" name="AllowancesPaymentType2" label="Payment Type" HcmData="1" SortOrder="39">
                <mandatoryIfNotEmpty name="AllowancesType2"></mandatoryIfNotEmpty>
                <options>
                    <option value=""></option>
                    <option value="One Time">One Time</option>
                    <option value="Recurring">Recurring</option>
                </options>
            </element>
            <element type="text" name="AllowancesAmountUnits2" label="Amount/Units" HcmData="1" SortOrder="40">
                <mandatoryIfNotEmpty name="AllowancesType2"></mandatoryIfNotEmpty>
                <regex inherit="amountwithdelimiter" pattern="" message=""></regex>
            </element>
            <element type="select" name="AllowancesNetGross2" label="Net/Gross" HcmData="1" SortOrder="41">
                <mandatoryIfNotEmpty name="AllowancesType2"></mandatoryIfNotEmpty>
                <options>
                    <option value=""></option>
                    <option value="Net">Net</option>
                    <option value="Gross">Gross</option>
                </options>
            </element>
            <element type="date" name="AllowancesValidFrom2" label="Valid from:" format="dd.MM.yyyy" HcmData="1" SortOrder="42">
                <mandatoryIfNotEmpty name="AllowancesType2"></mandatoryIfNotEmpty>
                <regex inherit="date" pattern="" message=""></regex>
                <laterThanOrEqual name="ChangeValidFrom" message="This date cannot be earlier than Change valid from date."></laterThanOrEqual>
            </element>
            <element type="date" name="AllowancesValidTo2" label="Valid to:"  default="31.12.9999" format="dd.MM.yyyy" HcmData="1" SortOrder="43">
                <regex inherit="date" pattern="" message=""></regex>
            </element>

            <element type="select" name="AllowancesType3" label="Allowance Type" HcmData="1" SortOrder="44">
                &data_changeallowancetype;
            </element>
            <element type="select" name="AllowancesPaymentType3" label="Payment Type" HcmData="1" SortOrder="45">
                <mandatoryIfNotEmpty name="AllowancesType3"></mandatoryIfNotEmpty>
                <options>
                    <option value=""></option>
                    <option value="One Time">One Time</option>
                    <option value="Recurring">Recurring</option>
                </options>
            </element>
            <element type="text" name="AllowancesAmountUnits3" label="Amount/Units" HcmData="1" SortOrder="46">
                <mandatoryIfNotEmpty name="AllowancesType3"></mandatoryIfNotEmpty>
                <regex inherit="amountwithdelimiter" pattern="" message=""></regex>
            </element>
            <element type="select" name="AllowancesNetGross3" label="Net/Gross" HcmData="1" SortOrder="47">
                <mandatoryIfNotEmpty name="AllowancesType3"></mandatoryIfNotEmpty>
                <options>
                    <option value=""></option>
                    <option value="Net">Net</option>
                    <option value="Gross">Gross</option>
                </options>
            </element>
            <element type="date" name="AllowancesValidFrom3" label="Valid from:"  format="dd.MM.yyyy" HcmData="1" SortOrder="48">
                <mandatoryIfNotEmpty name="AllowancesType3"></mandatoryIfNotEmpty>
                <regex inherit="date" pattern="" message=""></regex>
                <laterThanOrEqual name="ChangeValidFrom" message="This date cannot be earlier than Change valid from date."></laterThanOrEqual>
            </element>
            <element type="date" name="AllowancesValidTo3" label="Valid to:"  default="31.12.9999" format="dd.MM.yyyy" HcmData="1" SortOrder="49">
                <regex inherit="date" pattern="" message=""></regex>
            </element>

            <element type="select" name="AllowancesType4" label="Allowance Type" HcmData="1" SortOrder="50">
                &data_changeallowancetype;
            </element>
            <element type="select" name="AllowancesPaymentType4" label="Payment Type" HcmData="1" SortOrder="51">
                <mandatoryIfNotEmpty name="AllowancesType4"></mandatoryIfNotEmpty>
                <options>
                    <option value=""></option>
                    <option value="One Time">One Time</option>
                    <option value="Recurring">Recurring</option>
                </options>
            </element>
            <element type="text" name="AllowancesAmountUnits4" label="Amount/Units" HcmData="1" SortOrder="52">
                <mandatoryIfNotEmpty name="AllowancesType4"></mandatoryIfNotEmpty>
                <regex inherit="amountwithdelimiter" pattern="" message=""></regex>
            </element>
            <element type="select" name="AllowancesNetGross4" label="Net/Gross" HcmData="1" SortOrder="53">
                <mandatoryIfNotEmpty name="AllowancesType4"></mandatoryIfNotEmpty>
                <options>
                    <option value=""></option>
                    <option value="Net">Net</option>
                    <option value="Gross">Gross</option>
                </options>
            </element>
            <element type="date" name="AllowancesValidFrom4" label="Valid from:"  format="dd.MM.yyyy" HcmData="1" SortOrder="54">
                <mandatoryIfNotEmpty name="AllowancesType4"></mandatoryIfNotEmpty>
                <regex inherit="date" pattern="" message=""></regex>
                <laterThanOrEqual name="ChangeValidFrom" message="This date cannot be earlier than Change valid from date."></laterThanOrEqual>
            </element>
            <element type="date" name="AllowancesValidTo4" label="Valid to:"  default="31.12.9999" format="dd.MM.yyyy" HcmData="1" SortOrder="55">
                <regex inherit="date" pattern="" message=""></regex>
            </element>

            <element type="select" name="AllowancesType5" label="Allowance Type" HcmData="1" SortOrder="56">
                &data_changeallowancetype;
            </element>
            <element type="select" name="AllowancesPaymentType5" label="Payment Type" HcmData="1" SortOrder="57">
                <mandatoryIfNotEmpty name="AllowancesType5"></mandatoryIfNotEmpty>
                <options>
                    <option value=""></option>
                    <option value="One Time">One Time</option>
                    <option value="Recurring">Recurring</option>
                </options>
            </element>
            <element type="text" name="AllowancesAmountUnits5" label="Amount/Units" HcmData="1" SortOrder="58">
                <mandatoryIfNotEmpty name="AllowancesType5"></mandatoryIfNotEmpty>
                <regex inherit="amountwithdelimiter" pattern="" message=""></regex>
            </element>
            <element type="select" name="AllowancesNetGross5" label="Net/Gross" HcmData="1" SortOrder="59">
                <mandatoryIfNotEmpty name="AllowancesType5"></mandatoryIfNotEmpty>
                <options>
                    <option value=""></option>
                    <option value="Net">Net</option>
                    <option value="Gross">Gross</option>
                </options>
            </element>
            <element type="date" name="AllowancesValidFrom5" label="Valid from:"  format="dd.MM.yyyy" HcmData="1" SortOrder="60">
                <mandatoryIfNotEmpty name="AllowancesType5"></mandatoryIfNotEmpty>
                <regex inherit="date" pattern="" message=""></regex>
                <laterThanOrEqual name="ChangeValidFrom" message="This date cannot be earlier than Change valid from date."></laterThanOrEqual>
            </element>
            <element type="date" name="AllowancesValidTo5" label="Valid to:"  default="31.12.9999" format="dd.MM.yyyy" HcmData="1" SortOrder="61">
                <regex inherit="date" pattern="" message=""></regex>
            </element>

          <!--Deductions-->
          <element type="hidden" default="1" name="Deductions"></element>
          <!--1-->
          <element name="DeductionsType" label="Deduction Type" type="select" HcmData="1" SortOrder="62">
            <mandatoryIfNotEmpty name="DeductionsAmountUnits"></mandatoryIfNotEmpty>
            <options>
              <option value=""></option>
              <option value="Company Fitness">Company Fitness</option>
            </options>
          </element>
          <element name="DeductionsPaymentType" label="Payment type" type="select" HcmData="1" SortOrder="63">
            <mandatoryIfNotEmpty name="DeductionsType"></mandatoryIfNotEmpty>
            <options>
              <option value=""></option>
              <option value="One Time">One Time</option>
              <option value="Recurring">Recurring</option>
            </options>
          </element>
          <element name="DeductionsAmountUnits" label="Deduction Amount/Units" type="text" HcmData="1" SortOrder="64">
            <regex inherit="amountwithdelimiter" pattern="" message=""></regex>
            <mandatoryIfNotEmpty name="DeductionsType"></mandatoryIfNotEmpty>
          </element>
          <element type="select" name="DeductionsNetGross" label="Net/Gross" HcmData="1" SortOrder="65">
            <mandatoryIfNotEmpty name="DeductionsType"></mandatoryIfNotEmpty>
            <options>
              <option value=""></option>
              <option value="Net">Net</option>
              <option value="Gross">Gross</option>
            </options>
          </element>
          <element name="DeductionsValidFrom" label="Deduction Valid from" type="date" format="dd.MM.yyyy" HcmData="1" SortOrder="66">
            <regex inherit="date" pattern="" message=""></regex>
            <mandatoryIfNotEmpty name="DeductionsType"></mandatoryIfNotEmpty>
            <laterThanOrEqual name="ChangeValidFrom" message="This date cannot be earlier than Change valid from date."></laterThanOrEqual>
          </element>
          <element name="DeductionsValidTo" label="Deduction Valid to" type="date"  default="31.12.9999" format="dd.MM.yyyy" HcmData="1" SortOrder="67">
            <regex inherit="date" pattern="" message=""></regex>
            <mandatoryIf name="DeductionsPaymentType">Recurring</mandatoryIf>
          </element>
          <!--2-->
          <element name="DeductionsType2" label="Deduction Type" type="select"  HcmData="1" SortOrder="68">
            <mandatoryIfNotEmpty name="DeductionAmountUnits2"></mandatoryIfNotEmpty>
            <options>
              <option value=""></option>
              <option value="Company Fitness">Company Fitness</option>
            </options>
          </element>
          <element name="DeductionsPaymentType2" label="Payment type" type="select" HcmData="1" SortOrder="69">
            <mandatoryIfNotEmpty name="DeductionsType2"></mandatoryIfNotEmpty>
            <options>
              <option value=""></option>
              <option value="One Time">One Time</option>
              <option value="Recurring">Recurring</option>
            </options>
          </element>
          <element name="DeductionsAmountUnits2" label="Deduction Amount/Units" type="text" HcmData="1" SortOrder="70">
            <regex inherit="amountwithdelimiter" pattern="" message=""></regex>
            <mandatoryIfNotEmpty name="DeductionsType2"></mandatoryIfNotEmpty>
          </element>
          <element type="select" name="DeductionsNetGross2" label="Net/Gross" HcmData="1" SortOrder="71">
            <mandatoryIfNotEmpty name="DeductionsType2"></mandatoryIfNotEmpty>
            <options>
              <option value=""></option>
              <option value="Net">Net</option>
              <option value="Gross">Gross</option>
            </options>
          </element>
          <element name="DeductionsValidFrom2" label="Deduction Valid from" type="date" format="dd.MM.yyyy" HcmData="1" SortOrder="72">
            <regex inherit="date" pattern="" message=""></regex>
            <mandatoryIfNotEmpty name="DeductionsType2"></mandatoryIfNotEmpty>
            <laterThanOrEqual name="ChangeValidFrom" message="This date cannot be earlier than Change valid from date."></laterThanOrEqual>
          </element>
          <element name="DeductionsValidTo2" label="Deduction Valid to" type="date"  default="31.12.9999" format="dd.MM.yyyy" HcmData="1" SortOrder="73">
            <regex inherit="date" pattern="" message=""></regex>
            <mandatoryIf name="DeductionsPaymentType2">Recurring</mandatoryIf>
          </element>
          <!--3-->
          <element name="DeductionsType3" label="Deduction Type" type="select" HcmData="1" SortOrder="74">
            <mandatoryIfNotEmpty name="DeductionAmountUnits3"></mandatoryIfNotEmpty>
            <options>
              <option value=""></option>
              <option value="Company Fitness">Company Fitness</option>
            </options>
          </element>
          <element name="DeductionsPaymentType3" label="Payment type" type="select" HcmData="1" SortOrder="75">
            <mandatoryIfNotEmpty name="DeductionsType3"></mandatoryIfNotEmpty>
            <options>
              <option value=""></option>
              <option value="One Time">One Time</option>
              <option value="Recurring">Recurring</option>
            </options>
          </element>
          <element name="DeductionsAmountUnits3" label="Deduction Amount/Units" type="text" HcmData="1" SortOrder="76">
            <regex inherit="amountwithdelimiter" pattern="" message=""></regex>
            <mandatoryIfNotEmpty name="DeductionsType3"></mandatoryIfNotEmpty>
          </element>
          <element type="select" name="DeductionsNetGross3" label="Net/Gross" HcmData="1" SortOrder="77">
            <mandatoryIfNotEmpty name="DeductionsType3"></mandatoryIfNotEmpty>
            <options>
              <option value=""></option>
              <option value="Net">Net</option>
              <option value="Gross">Gross</option>
            </options>
          </element>
          <element name="DeductionsValidFrom3" label="Deduction Valid from" type="date" format="dd.MM.yyyy" HcmData="1" SortOrder="78">
            <regex inherit="date" pattern="" message=""></regex>
            <mandatoryIfNotEmpty name="DeductionsType3"></mandatoryIfNotEmpty>
            <laterThanOrEqual name="ChangeValidFrom" message="This date cannot be earlier than Change valid from date."></laterThanOrEqual>
          </element>
          <element name="DeductionsValidTo3" label="Deduction Valid to" type="date"  default="31.12.9999" format="dd.MM.yyyy" HcmData="1" SortOrder="79">
            <regex inherit="date" pattern="" message=""></regex>
            <mandatoryIf name="DeductionsPaymentType3">Recurring</mandatoryIf>
          </element>
          <!--4-->
          <element name="DeductionsType4" label="Deduction Type" type="select" HcmData="1" SortOrder="80">
            <mandatoryIfNotEmpty name="DeductionAmountUnits4"></mandatoryIfNotEmpty>
            <options>
              <option value=""></option>
              <option value="Company Fitness">Company Fitness</option>
            </options>
          </element>
          <element name="DeductionsPaymentType4" label="Payment type" type="select" HcmData="1" SortOrder="81">
            <mandatoryIfNotEmpty name="DeductionsType4"></mandatoryIfNotEmpty>
            <options>
              <option value=""></option>
              <option value="One Time">One Time</option>
              <option value="Recurring">Recurring</option>
            </options>
          </element>
          <element name="DeductionsAmountUnits4" label="Deduction Amount/Units" type="text" HcmData="1" SortOrder="82">
            <regex inherit="amountwithdelimiter" pattern="" message=""></regex>
            <mandatoryIfNotEmpty name="DeductionsType4"></mandatoryIfNotEmpty>
          </element>
          <element type="select" name="DeductionsNetGross4" label="Net/Gross" HcmData="1" SortOrder="83">
            <mandatoryIfNotEmpty name="DeductionsType4"></mandatoryIfNotEmpty>
            <options>
              <option value=""></option>
              <option value="Net">Net</option>
              <option value="Gross">Gross</option>
            </options>
          </element>
          <element name="DeductionsValidFrom4" label="Deduction Valid from" type="date" format="dd.MM.yyyy" HcmData="1" SortOrder="84">
            <regex inherit="date" pattern="" message=""></regex>
            <mandatoryIfNotEmpty name="DeductionsType4"></mandatoryIfNotEmpty>
            <laterThanOrEqual name="ChangeValidFrom" message="This date cannot be earlier than Change valid from date."></laterThanOrEqual>
          </element>
          <element name="DeductionsValidTo4" label="Deduction Valid to" type="date"  default="31.12.9999" format="dd.MM.yyyy" HcmData="1" SortOrder="85">
            <regex inherit="date" pattern="" message=""></regex>
            <mandatoryIf name="DeductionsPaymentType4">Recurring</mandatoryIf>
          </element>
          <!--5-->
          <element name="DeductionsType5" label="Deduction Type" type="select" HcmData="1" SortOrder="86">
            <mandatoryIfNotEmpty name="DeductionAmountUnits5"></mandatoryIfNotEmpty>
            <options>
              <option value=""></option>
              <option value="Company Fitness">Company Fitness</option>
            </options>
          </element>
          <element name="DeductionsPaymentType5" label="Payment type" type="select" HcmData="1" SortOrder="87">
            <mandatoryIfNotEmpty name="DeductionsType5"></mandatoryIfNotEmpty>
            <options>
              <option value=""></option>
              <option value="One Time">One Time</option>
              <option value="Recurring">Recurring</option>
            </options>
          </element>
          <element name="DeductionsAmountUnits5" label="Deduction Amount/Units" type="text" HcmData="1" SortOrder="88">
            <regex inherit="amountwithdelimiter" pattern="" message=""></regex>
            <mandatoryIfNotEmpty name="DeductionsType5"></mandatoryIfNotEmpty>
          </element>
          <element type="select" name="DeductionsNetGross5" label="Net/Gross" HcmData="1" SortOrder="89">
            <mandatoryIfNotEmpty name="DeductionsType5"></mandatoryIfNotEmpty>
            <options>
              <option value=""></option>
              <option value="Net">Net</option>
              <option value="Gross">Gross</option>
            </options>
          </element>
          <element name="DeductionsValidFrom5" label="Deduction Valid from" type="date" format="dd.MM.yyyy" HcmData="1" SortOrder="90">
            <regex inherit="date" pattern="" message=""></regex>
            <mandatoryIfNotEmpty name="DeductionsType5"></mandatoryIfNotEmpty>
            <laterThanOrEqual name="ChangeValidFrom" message="This date cannot be earlier than Change valid from date."></laterThanOrEqual>
          </element>
          <element name="DeductionsValidTo5" label="Deduction Valid to" type="date"  default="31.12.9999" format="dd.MM.yyyy" HcmData="1" SortOrder="91">
            <regex inherit="date" pattern="" message=""></regex>
            <mandatoryIf name="DeductionsPaymentType5">Recurring</mandatoryIf>
          </element>
          <element type="select" name="OneIKEABonusLevel" label="One IKEA Bonus Level "  HcmData="1" SortOrder="117">
            <options>
              <option value=""></option>
              <option value="Level 1">Level 1</option>
              <option value="Level 2">Level 2</option>
              <option value="Level 3">Level 3</option>
            </options>
          </element>
          
          <!--Benefits-->
            <element type="hidden" name="Benefits" default="1"></element>
            <element type="select" name="TypeOfBenefit" label="Type of benefit" HcmData="1" SortOrder="92">
                &data_typeofbenefit;
            </element>
            <element type="select" name="Category" label="Category" HcmData="1" SortOrder="93">
                <mandatoryIf name="TypeOfBenefit">Company Car</mandatoryIf>
                <options>
                    <option value=""></option>
                    <option value="Class 1">Class 1</option>
                    <option value="Class 2">Class 2</option>
                </options>
            </element>
            <element type="select" name="TypeOfCar" label="Type of car" HcmData="1" SortOrder="94">
                <mandatoryIf name="TypeOfBenefit">Company Car</mandatoryIf>
                <options>
                    <option value=""></option>
                    <option value="necessity car without the option to drive privately">necessity car without the option to drive privately</option>
                    <option value="necessity car with the option to drive privately by paying € 250,- net a month">necessity car with the option to drive privately by paying € 250,- net a month</option>
                    <option value="benefit car, for business and private use">benefit car, for business and private use</option>
                </options>
            </element>
            <element type="text" name="MonthlyAmount" label="Monthly Amount"  HcmData="1" SortOrder="95">
                <regex inherit="amountwithdelimiter" pattern="" message=""></regex>
            </element>
            <element type="date" name="NextRevisionDate" label="Next Revision Date" future="1" format="dd.MM.yyyy" HcmData="1" SortOrder="96">
                <mandatoryIf name="TypeOfBenefit">Salary Revision</mandatoryIf>
                <regex inherit="date" message="" pattern=""></regex>
            </element>
            <element type="select" name="TypeOfBenefit2" label="Type of benefit" HcmData="1" SortOrder="97">
                &data_typeofbenefit;
            </element>
            <element type="select" name="Category2" label="Category" HcmData="1" SortOrder="98">
                <mandatoryIf name="TypeOfBenefit2">Company Car</mandatoryIf>
                <options>
                    <option value=""></option>
                    <option value="Class 1">Class 1</option>
                    <option value="Class 2">Class 2</option>
                </options>
            </element>
            <element type="select" name="TypeOfCar2" label="Type of car" HcmData="1" SortOrder="99">
                <mandatoryIf name="TypeOfBenefit2">Company Car</mandatoryIf>
                <options>
                    <option value=""></option>
                    <option value="necessity car without the option to drive privately">necessity car without the option to drive privately</option>
                    <option value="necessity car with the option to drive privately by paying € 250,- net a month">necessity car with the option to drive privately by paying € 250,- net a month</option>
                    <option value="benefit car, for business and private use">benefit car, for business and private use</option>
                </options>
            </element>
            <element type="text" name="MonthlyAmount2" label="Monthly Amount" HcmData="1" SortOrder="100">
              <regex inherit="amountwithdelimiter" pattern="" message=""></regex>
            </element>
            <element type="date" name="NextRevisionDate2" label="Next Revision Date" future="1" format="dd.MM.yyyy" HcmData="1" SortOrder="101">
                <mandatoryIf name="TypeOfBenefit2">Salary Revision</mandatoryIf>
                <regex inherit="date" message="" pattern=""></regex>
            </element>


            <element type="select" name="TypeOfBenefit3" label="Type of benefit" HcmData="1" SortOrder="102">
                &data_typeofbenefit;
            </element>
            <element type="select" name="Category3" label="Category" HcmData="1" SortOrder="103">
                <mandatoryIf name="TypeOfBenefit3">Company Car</mandatoryIf>
                <options>
                    <option value=""></option>
                    <option value="Class 1">Class 1</option>
                    <option value="Class 2">Class 2</option>
                </options>
            </element>
            <element type="select" name="TypeOfCar3" label="Type of car" HcmData="1" SortOrder="104">
                <mandatoryIf name="TypeOfBenefit3">Company Car</mandatoryIf>
                <options>
                    <option value=""></option>
                    <option value="necessity car without the option to drive privately">necessity car without the option to drive privately</option>
                    <option value="necessity car with the option to drive privately by paying € 250,- net a month">necessity car with the option to drive privately by paying € 250,- net a month</option>
                    <option value="benefit car, for business and private use">benefit car, for business and private use</option>
                </options>
            </element>
            <element type="text" name="MonthlyAmount3" label="Monthly Amount" HcmData="1" SortOrder="105">
              <regex inherit="amountwithdelimiter" pattern="" message=""></regex>
            </element>
            <element type="date" name="NextRevisionDate3" label="Next Revision Date" future="1" format="dd.MM.yyyy" HcmData="1" SortOrder="106">
                <mandatoryIf name="TypeOfBenefit3">Salary Revision</mandatoryIf>
                <regex inherit="date" message="" pattern=""></regex>
            </element>

            <element type="select" name="TypeOfBenefit4" label="Type of benefit" HcmData="1" SortOrder="107">
                &data_typeofbenefit;
            </element>
            <element type="select" name="Category4" label="Category" HcmData="1" SortOrder="108">
                <mandatoryIf name="TypeOfBenefit4">Company Car</mandatoryIf>
                <options>
                    <option value=""></option>
                    <option value="Class 1">Class 1</option>
                    <option value="Class 2">Class 2</option>
                </options>
            </element>
            <element type="select" name="TypeOfCar4" label="Type of car" HcmData="1" SortOrder="109">
                <mandatoryIf name="TypeOfBenefit4">Company Car</mandatoryIf>
                <options>
                    <option value=""></option>
                    <option value="necessity car without the option to drive privately">necessity car without the option to drive privately</option>
                    <option value="necessity car with the option to drive privately by paying € 250,- net a month">necessity car with the option to drive privately by paying € 250,- net a month</option>
                    <option value="benefit car, for business and private use">benefit car, for business and private use</option>
                </options>
            </element>
            <element type="text" name="MonthlyAmount4" label="Monthly Amount" HcmData="1" SortOrder="110">
              <regex inherit="amountwithdelimiter" pattern="" message=""></regex>
            </element>
            <element type="date" name="NextRevisionDate4" label="Next Revision Date" future="1" format="dd.MM.yyyy" HcmData="1" SortOrder="111">
                <mandatoryIf name="TypeOfBenefit4">Salary Revision</mandatoryIf>
                <regex inherit="date" message="" pattern=""></regex>
            </element>

            <element type="select" name="TypeOfBenefit5" label="Type of benefit" HcmData="1" SortOrder="112">
                &data_typeofbenefit;
            </element>
            <element type="select" name="Category5" label="Category" HcmData="1" SortOrder="113">
                <mandatoryIf name="TypeOfBenefit5">Company Car</mandatoryIf>
                <options>
                    <option value=""></option>
                    <option value="Class 1">Class 1</option>
                    <option value="Class 2">Class 2</option>
                </options>
            </element>
            <element type="select" name="TypeOfCar5" label="Type of car" HcmData="1" SortOrder="114">
                <mandatoryIf name="TypeOfBenefit5">Company Car</mandatoryIf>
                <options>
                    <option value=""></option>
                    <option value="necessity car without the option to drive privately">necessity car without the option to drive privately</option>
                    <option value="necessity car with the option to drive privately by paying € 250,- net a month">necessity car with the option to drive privately by paying € 250,- net a month</option>
                    <option value="benefit car, for business and private use">benefit car, for business and private use</option>
                </options>
            </element>
            <element type="text" name="MonthlyAmount5" label="Monthly Amount" HcmData="1" SortOrder="115">
              <regex inherit="amountwithdelimiter" pattern="" message=""></regex>
            </element>
            <element type="date" name="NextRevisionDate5" label="Next Revision Date" future="1" format="dd.MM.yyyy" HcmData="1" SortOrder="116">
                <mandatoryIf name="TypeOfBenefit5">Salary Revision</mandatoryIf>
                <regex inherit="date" message="" pattern=""></regex>
            </element>
        </tab>
    </fields>
</form>