<?xml version="1.0" encoding="utf-8" ?>
<predefined>
  <name>Function_Department_Linemanager</name>
  <dependent>
    <selected>Steering Group_Customer Relations Dublin Store</selected>
    <show1>7010 - Management Group</show1>
    <show2>Claudia Marshall</show2>
  </dependent>
  <dependent>
    <selected>Comm-In_Comm In Dublin Store</selected>
    <show1>7010 - Management Group</show1>
    <show2>Miranda Lyons</show2>
  </dependent>
  <dependent>
    <selected>Steering Group_Comm In Dublin Store</selected>
    <show1>7010 - Management Group</show1>
    <show2>James Lindsay</show2>
  </dependent>
  <dependent>
    <selected>Bus Navigation_Business Navigation Service Office</selected>
    <show1>7010 - MANAGEMENT GROUP</show1>
    <show2></show2>
  </dependent>
  <dependent>
    <selected>Cust Relations_Customer Services Dublin Store</selected>
    <show1>6121 - After Sales Mng</show1>
    <show2></show2>
  </dependent>
  <dependent>
    <selected>Sales_Markethall Dublin Store</selected>
    <show1>7010 - Management Group</show1>
    <show2>Chris Kelly</show2>
  </dependent>
  <dependent>
    <selected>Comm-In_Visual Merchandising Dublin Store</selected>
    <show1>6071 - Communic &amp; Interior</show1>
    <show2>Aileen Curran</show2>
  </dependent>
  <dependent>
    <selected>Bus Navigation_Business Navigation Dublin Store</selected>
    <show1>6210 - Administration</show1>
    <show2>Andrea Nagy</show2>
  </dependent>
  <dependent>
    <selected>Sales_HFB 4,5 Bedrooms Dublin Store</selected>
    <show1>3340 - Bedrooms</show1>
    <show2>Marie Marsh</show2>
  </dependent>
  <dependent>
    <selected>Cust Relations_Customer Fulfillment Dublin Store</selected>
    <show1>6120 - CS After Sales Serv</show1>
    <show2>Tina McDonald-Sisk</show2>
  </dependent>
  <dependent>
    <selected>IKEA Food Serv_Restaurant Dublin Store</selected>
    <show1>3921 - Restaurant Mng</show1>
    <show2></show2>
  </dependent>
  <dependent>
    <selected>Logistics_Goods Flow Team 1 Full Serve Dublin Sto</selected>
    <show1>4050 - Full Serve/ EMPU</show1>
    <show2>Edward O'Toole</show2>
  </dependent>
  <dependent>
    <selected>Sales_Showroom Dublin Store</selected>
    <show1>3320 - Living Rooms</show1>
    <show2>Sally Kenny</show2>
  </dependent>
  <dependent>
    <selected>Logistics_Goods Flow Team 3 Goods Flow Dublin Sto</selected>
    <show1>4030 - Goods Receiving</show1>
    <show2>Brian Harvey</show2>
  </dependent>
  <dependent>
    <selected>Sales_HFB 7,8 Kitchens Dublin Store</selected>
    <show1>3360 - Kitchen</show1>
    <show2>Leandro Godoy</show2>
  </dependent>
  <dependent>
    <selected>Sales_HFB 18,19 Home Org Dublin Store</selected>
    <show1>3550 - Homeorg&amp;Second Stora</show1>
    <show2>Chris Kelly</show2>
  </dependent>
  <dependent>
    <selected>Logistics_Sales Supply Support Dublin Store</selected>
    <show1>4020 - Stock Control</show1>
    <show2>Edward O'Toole</show2>
  </dependent>
  <dependent>
    <selected>Sales_Self Serve Dublin Store</selected>
    <show1>3400 - Self Serve</show1>
    <show2>Paul Flood</show2>
  </dependent>
  <dependent>
    <selected>Logistics_Goods Flow Dublin Store</selected>
    <show1>4030 - Goods Receiving</show1>
    <show2>Scott Fairbairn</show2>
  </dependent>
  <dependent>
    <selected>Sales_HFB 10 Lighting Dublin Store</selected>
    <show1>3520 - Lighting</show1>
    <show2>Chris Kelly</show2>
  </dependent>
  <dependent>
    <selected>Operations_Facility management</selected>
    <show1>6830 - FACILITY MANAGEMENT</show1>
    <show2>Ian Randle</show2>
  </dependent>
  <dependent>
    <selected>Cust Relations_Checkout Services Dublin Store</selected>
    <show1>6190 - Cash Administration</show1>
    <show2>Ross Sharp</show2>
  </dependent>
  <dependent>
    <selected>Steering Group_IKEA Food Dublin Store</selected>
    <show1>3921 - Restaurant Mng</show1>
    <show2>Claudia Marshall</show2>
  </dependent>
  <dependent>
    <selected>IKEA Food Serv_IF Kitchen Dublin Store</selected>
    <show1>3923 - Restaurant Kitchen</show1>
    <show2>Kresimir Jurisic</show2>
  </dependent>
  <dependent>
    <selected>Logistics_Goods Flow Team 2 Replen Dublin Store</selected>
    <show1>4040 - Goods Replenishment</show1>
    <show2>Scott Fairbairn</show2>
  </dependent>
  <dependent>
    <selected>HR_HR Admin Dublin Store</selected>
    <show1>6600 - Human Resource</show1>
    <show2>Aoife Joyce</show2>
  </dependent>
  <dependent>
    <selected>Comm-In_Graphic Communication Dublin Store</selected>
    <show1>6071 - Communic &amp; Interior</show1>
    <show2>Brid Casey</show2>
  </dependent>
  <dependent>
    <selected>OCP Dublin_Home Furnishing Dublin Carr. OCP</selected>
    <show1>6204 - Support other(s) 3</show1>
    <show2>Kieran Clancy</show2>
  </dependent>
  <dependent>
    <selected>Steering Group_Marketing Dublin Store</selected>
    <show1>7010 - Management Group</show1>
    <show2>Charlotte Hanlon</show2>
  </dependent>
  <dependent>
    <selected>Sales_HFB 16,17 Home Dec Dublin Store</selected>
    <show1>3560 - Decoration# Outd&amp;Oth</show1>
    <show2>Chris Kelly</show2>
  </dependent>
  <dependent>
    <selected>IKEA Food Serv_IKEA Food Dublin Store</selected>
    <show1>3921 - Restaurant Mng</show1>
    <show2>Laragh King</show2>
  </dependent>
  <dependent>
    <selected>Sales_HFB 14,15 Cooking Eating Dublin Store</selected>
    <show1>3540 - Cooking &amp; Eating</show1>
    <show2></show2>
  </dependent>
  <dependent>
    <selected>Steering Group_Q Store Service Office</selected>
    <show1>6400 - Quality Common</show1>
    <show2>Mia-Maria Nordlund</show2>
  </dependent>
  <dependent>
    <selected>OCP Dublin_OCP Dublin Carrickmines</selected>
    <show1>6204 - Support other(s) 3</show1>
    <show2>Joanne Randle</show2>
  </dependent>
  <dependent>
    <selected>Sales_HFB 11,12,13 Textiles Dublin Store</selected>
    <show1>3530 - Textiles &amp; Rugs</show1>
    <show2>Danielle O'Hara</show2>
  </dependent>
  <dependent>
    <selected>Cust Relations_Customer Services Returns Dublin Store</selected>
    <show1>6122 - After Sales Returns</show1>
    <show2></show2>
  </dependent>
  <dependent>
    <selected>Comm-In_Interior Design Dublin Store</selected>
    <show1>6071 - Communic &amp; Interior</show1>
    <show2></show2>
  </dependent>
  <dependent>
    <selected>Sales_HFB 1,2 Living &amp; Storage Dublin Store</selected>
    <show1>3320 - Living Rooms</show1>
    <show2>Mark Dempsey</show2>
  </dependent>
  <dependent>
    <selected>Marketing_Marketing Dublin Store</selected>
    <show1>6073 - PR</show1>
    <show2>Charlotte Hanlon</show2>
  </dependent>
  <dependent>
    <selected>Cust Services_Customer Support Contact Centre</selected>
    <show1>7010 - MANAGEMENT GROUP</show1>
    <show2></show2>
  </dependent>
  <dependent>
    <selected>Bus Navigation_Q Store Service Office</selected>
    <show1>6400 - Quality Common</show1>
    <show2>Mia-Maria Nordlund</show2>
  </dependent>
  <dependent>
    <selected>IKEA Food Serv_Swedish Food Market Dublin Store</selected>
    <show1>3960 - IKEA Food Bistro</show1>
    <show2>Michal Adamczyk</show2>
  </dependent>
  <dependent>
    <selected>Operations_HFB 7,8 Kitchens Dublin Store</selected>
    <show1>3360 - Kitchen</show1>
    <show2>Leandro Godoy</show2>
  </dependent>
  <dependent>
    <selected>Sales_HFB 9 Childrens Dublin Store</selected>
    <show1>3370 - Children's IKEA</show1>
    <show2>Sally Kenny</show2>
  </dependent>
  <dependent>
    <selected>Logistics_Goodsflow Services Dublin Store</selected>
    <show1>4030 - Goods Receiving</show1>
    <show2></show2>
  </dependent>
  <dependent>
    <selected>Operations_Safety &amp; Security Dublin Store</selected>
    <show1>6340 - Safety &amp; Security 2</show1>
    <show2>Claudia Marshall</show2>
  </dependent>
  <dependent>
    <selected>Operations_Recovery Dublin Store</selected>
    <show1>6330 - IKEA Green (Rec&amp;Env)</show1>
    <show2>Kresimir Kovacevic</show2>
  </dependent>
  <dependent>
    <selected>OCP Dublin_Customer Experience Dublin Carr. OCP</selected>
    <show1>6204 - Support other(s) 3</show1>
    <show2>Nicola Mac Inerney</show2>
  </dependent>
  <dependent>
    <selected>Sales_HFB 3 Work IKEA Dublin Store</selected>
    <show1>3350 - Work IKEA</show1>
    <show2>Rachel Starrs</show2>
  </dependent>
  <dependent>
    <selected>HR_Human Resources Dublin Store</selected>
    <show1>7010 - Management Group</show1>
    <show2>Aoife McCarthy</show2>
  </dependent>
  <dependent>
    <selected>Cust Relations_HFB 4,5 Bedrooms Dublin Store</selected>
    <show1>3340 - Bedrooms</show1>
    <show2>Marie Marsh</show2>
  </dependent>
  <dependent>
    <selected>Sales_HFB 6 Bathshop Dublin Store</selected>
    <show1>3380 - Bathroom</show1>
    <show2>Paul Ringwood</show2>
  </dependent>
  <dependent>
    <selected>Sales_Activities Dublin Store</selected>
    <show1>3570 - Activity</show1>
    <show2></show2>
  </dependent>
  <dependent>
    <selected>Bus Navigation_Business Nav 3 Service Office</selected>
    <show1>7010 - MANAGEMENT GROUP</show1>
    <show2></show2>
  </dependent>
  <dependent>
    <selected>Cust Relations_Customer Relations Dublin Store</selected>
    <show1>6180 - CS Cash</show1>
    <show2>Tina McDonald-Sisk</show2>
  </dependent>
  <dependent>
    <selected>Steering Group_Business Navigation Dublin Store</selected>
    <show1>7010 - Management Group</show1>
    <show2>Claudia Marshall</show2>
  </dependent>
  <dependent>
    <selected>Steering Group_Sales/Commercial Dublin Store</selected>
    <show1>7010 - Management Group</show1>
    <show2>James Lindsay</show2>
  </dependent>
  <dependent>
    <selected>Logistics_Logistics Dublin Store</selected>
    <show1>7010 - Management Group</show1>
    <show2>James Lindsay</show2>
  </dependent>
  <dependent>
    <selected>Sales_Home Furnishing Dublin Carr. OCP</selected>
    <show1>6204 - Support other(s) 3</show1>
    <show2>Kieran Clancy</show2>
  </dependent>
  <dependent>
    <selected>Operations_Retail Property</selected>
    <show1>6810 - RETAIL ESTABLISHMENT</show1>
    <show2>Claudia Marshall</show2>
  </dependent>
  <dependent>
    <selected>Cust Relations_Customer Relations Service Office</selected>
    <show1>7010 - MANAGEMENT GROUP</show1>
    <show2>Donna Marie Moore</show2>
  </dependent>
  <dependent>
    <selected>Operations_IT Service Office</selected>
    <show1>6299 - RE-INVOICE INTERCMP</show1>
    <show2>Ben Rosser</show2>
  </dependent>
  <dependent>
    <selected>Bus Navigation_Business Nav 2 Service Office</selected>
    <show1>7010 - MANAGEMENT GROUP</show1>
    <show2>Linton John Scarborough</show2>
  </dependent>
  <dependent>
    <selected>Bus Navigation_IT</selected>
    <show1>6299 - RE-INVOICE INTERCMP</show1>
    <show2>Steven Lam</show2>
  </dependent>
  <dependent>
    <selected>Steering Group_Internationals Dublin Store</selected>
    <show1>6299 - Re-Invoice Intercmp</show1>
    <show2>Claudia Marshall</show2>
  </dependent>
  <dependent>
    <selected>Bus Navigation_Business Nav 1 Service Office</selected>
    <show1>6232 - CONTROLLING / BN</show1>
    <show2>Sajal Shah</show2>
  </dependent>
  <dependent>
    <selected>Steering Group_Store Dublin 038</selected>
    <show1>7010 - Management Group</show1>
    <show2>Gillian Drakeford</show2>
  </dependent>
  <dependent>
    <selected>Comm- In_CommIn Service Office</selected>
    <show1>6299 - RE-INVOICE INTERCMP</show1>
    <show2>Jill Reedman</show2>
  </dependent>
  <dependent>
    <selected>Marketing_Marketing Service Office</selected>
    <show1>7010 - MANAGEMENT GROUP</show1>
    <show2>Laurent Tiersen</show2>
  </dependent>
  <dependent>
    <selected>Marketing_Sustainability</selected>
    <show1>7011 - Management Support</show1>
    <show2>Hege Saebjornsen</show2>
  </dependent>
  <dependent>
    <selected>Sales_Sales Service Office</selected>
    <show1>6241 - BUSINESS SUPPORT 1</show1>
    <show2>Laura Addison</show2>
  </dependent>
</predefined>
